{"student_id":"ikleiman@stonybrook.edu","patient_id":"1","trial_number":1,"response":"Patient's antihypertensive regimen was overdosed, and he returns with symptomatic hypotension. Patient was to have his home amlodipine dose continued. \nHis cholesterol medication was underdosed, and he returns with chest pain. He requires that his home regimen of atorvastatin be continued. \n","correct":false,"submitted_time":"2019-11-04","elapsed_time_sec":7,"submission":{"group_1":{"Amlodipine_Home":{"amt":"10","action":"modify"},"Amlodipine_Hospital":{"amt":"10","action":"modify"}},"group_2":{"Gabapentin_Home":{"amt":"200","action":"modify"},"Gabapentin_Hospital":{"amt":"200","action":"modify"}},"group_3":{"Pravastatin_Home":{"amt":"20","action":"modify"},"Simvastatin_Hospital":{"amt":"10","action":"modify"}},"group_4":{"Acetaminophen_Hospital":{"amt":"2400","action":"modify"}}},"submit_amt":{"group_1":20,"group_2":400,"group_3":30,"group_4":2400},"actual_amt":{"group_1":5,"group_2":400,"group_3":40,"group_4":2400}}